simple_dmessage.py
simple_dmessage-0.2.0.dist-info/METADATA
simple_dmessage-0.2.0.dist-info/WHEEL
simple_dmessage-0.2.0.dist-info/RECORD
