Metadata-Version: 2.1
Name: simple-dmessage
Version: 0.2.0
Summary: A package for sending direct messages via Discord
Author: Lee Kin Emree
Author-email: nspielman@live.com
Requires-Python: >=3.9,<4.0
Classifier: Programming Language :: Python :: 3
Classifier: Programming Language :: Python :: 3.9
Classifier: Programming Language :: Python :: 3.10
Classifier: Programming Language :: Python :: 3.11
Requires-Dist: discord.py (>=2.0.0,<3.0.0)
